bokeh_plot/1.py
bokeh_plot/__init__.py
bokeh_plot/a.py
bokeh_plot/b.py
bokeh_plot/parser.py
bokeh_plot-0.1.22.dist-info/LICENSE
bokeh_plot-0.1.22.dist-info/METADATA
bokeh_plot-0.1.22.dist-info/WHEEL
bokeh_plot-0.1.22.dist-info/top_level.txt
bokeh_plot-0.1.22.dist-info/RECORD
