Metadata-Version: 2.1
Name: bokeh-plot
Version: 0.1.22
Summary: Matlab-inspired call syntax for bokeh plots
Home-page: https://github.com/axil/bokeh-plot
Author: Lev Maximov
Author-email: lev.maximov@gmail.com
License: MIT License
Keywords: bokeh,jupyter,notebook,plot
Platform: UNKNOWN
Classifier: Programming Language :: Python :: 3
Classifier: License :: OSI Approved :: MIT License
Classifier: Operating System :: OS Independent
License-File: LICENSE
Requires-Dist: bokeh
